{"version":1,"resource":"file:///home/guillem/.config/polybar/modules.ini","entries":[{"id":"SC8P.ini","timestamp":1694208920814},{"id":"Qgf9.ini","timestamp":1694209206511},{"id":"hIz4.ini","source":"undoRedo.source","timestamp":1694209211639},{"id":"ta9N.ini","timestamp":1694209227191},{"id":"xcLy.ini","timestamp":1694209262296},{"id":"vdMv.ini","timestamp":1694209295372},{"id":"zFGo.ini","timestamp":1694209321913},{"id":"WKGV.ini","timestamp":1694209338189},{"id":"0fyF.ini","timestamp":1694209396254},{"id":"FK64.ini","timestamp":1694209410566},{"id":"VFjY.ini","timestamp":1694209434403},{"id":"8kAm.ini","timestamp":1694209458867},{"id":"m8rg.ini","timestamp":1694209482048},{"id":"cPbo.ini","timestamp":1694209532401},{"id":"feAV.ini","timestamp":1694209548589}]}